architectures/DenseNet.py
architectures/LeNet.py
architectures/MKToyNet.py
architectures/ResNet.py
architectures/WideResNet.py
architectures/__init__.py
Robustness_Framework-0.0.3.dist-info/METADATA
Robustness_Framework-0.0.3.dist-info/WHEEL
Robustness_Framework-0.0.3.dist-info/top_level.txt
Robustness_Framework-0.0.3.dist-info/RECORD
