Metadata-Version: 2.1
Name: Robustness-Framework
Version: 0.0.3
Summary: An efficient framework for establishing a baseline for standard and adversarial machine learning training projects 
Home-page: https://github.com/khalooei/robustness-framework
Author: Mohammad KHalooei
Author-email: mkhalooei90@gmail.com
License: UNKNOWN
Platform: UNKNOWN
Classifier: Programming Language :: Python :: 3
Classifier: License :: OSI Approved :: MIT License
Classifier: Operating System :: OS Independent
Requires-Python: >=3.8
